black_cgx.py
black_cgx-0.1.0.dist-info/entry_points.txt
black_cgx-0.1.0.dist-info/LICENSE
black_cgx-0.1.0.dist-info/WHEEL
black_cgx-0.1.0.dist-info/METADATA
black_cgx-0.1.0.dist-info/RECORD
